pyuptimerobot/__init__.py
pyuptimerobot/const.py
pyuptimerobot/decorator.py
pyuptimerobot/exceptions.py
pyuptimerobot/models.py
pyuptimerobot/uptimerobot.py
pyuptimerobot-23.1.0.dist-info/LICENSE
pyuptimerobot-23.1.0.dist-info/METADATA
pyuptimerobot-23.1.0.dist-info/WHEEL
pyuptimerobot-23.1.0.dist-info/top_level.txt
pyuptimerobot-23.1.0.dist-info/RECORD
