Metadata-Version: 2.1
Name: pyuptimerobot
Version: 23.1.0
Summary: Python API wrapper for Uptime Robot.
Home-page: https://github.com/ludeeus/pyuptimerobot
Author: Joakim Sorensen
Author-email: hi@ludeeus.dev
License: MIT license
Keywords: homeassistant,version,update
Classifier: Intended Audience :: Developers
Classifier: License :: OSI Approved :: MIT License
Classifier: Natural Language :: English
Classifier: Programming Language :: Python :: 3
Classifier: Programming Language :: Python :: 3.8
Classifier: Programming Language :: Python :: 3.9
Classifier: Programming Language :: Python :: 3.10
Classifier: Topic :: Software Development :: Libraries :: Python Modules
Requires-Python: >=3.8.0
License-File: LICENSE
Requires-Dist: aiohttp (<4.0,>=3.6.1)
